<mxGraphModel style="default-style2"><root><mxCell id="0"/><mxCell id="1" parent="0"/><mxCell id="2" value="depx github&#xa;&#xa;" style="ellipse;shape=cloud;fontStyle=1" vertex="1" parent="1"><mxGeometry x="245" y="159" width="230" height="130" as="geometry"/></mxCell><mxCell id="3" value="http://depx.org&#xa;&#xa;" style="ellipse;shape=cloud;fontStyle=1" vertex="1" parent="1"><mxGeometry x="390" y="19" width="230" height="120" as="geometry"/></mxCell><mxCell id="4" value="depx  client" style="ellipse;shape=cloud;fontStyle=1" vertex="1" parent="1"><mxGeometry x="170" y="19" width="150" height="90" as="geometry"/></mxCell><mxCell id="5" value="" style="edgeStyle=none" edge="1" parent="1" source="2" target="4"><mxGeometry x="140" y="99" width="100" height="100" as="geometry"><mxPoint x="310" y="179" as="sourcePoint"/><mxPoint x="250" y="129" as="targetPoint"/></mxGeometry></mxCell><mxCell id="6" value="" style="edgeStyle=none" edge="1" parent="1" source="2" target="3"><mxGeometry x="150" y="109" width="100" height="100" as="geometry"><mxPoint x="332.458739268716" y="203.25627904176577" as="sourcePoint"/><mxPoint x="287.615711973282" y="144.72823873429184" as="targetPoint"/></mxGeometry></mxCell><mxCell id="10" value="submit your own&#xa;packages" style="shape=cube" vertex="1" parent="1"><mxGeometry x="280" y="379" width="180" height="80" as="geometry"/></mxCell><mxCell id="11" value="pull&#xa;request&#xa;" style="arrow" edge="1" parent="1"><mxGeometry x="72.5" y="-36" width="100" height="100" as="geometry"><mxPoint x="412.5" y="374" as="sourcePoint"/><mxPoint x="412.5" y="284" as="targetPoint"/><mxPoint x="-3" y="19.989797267639915" as="offset"/></mxGeometry></mxCell><mxCell id="12" value="FORK depx&#xa;" style="arrow" edge="1" parent="1"><mxGeometry x="220.74590292948386" y="209" width="100" height="100" as="geometry"><mxPoint x="332.5" y="279" as="sourcePoint"/><mxPoint x="332.5" y="379" as="targetPoint"/></mxGeometry></mxCell><mxCell id="15" value="your application" style="swimlane" vertex="1" parent="1"><mxGeometry x="30" y="189" width="150" height="140" as="geometry"/></mxCell><mxCell id="16" value="/lib" style="text" vertex="1" parent="15"><mxGeometry x="20" y="40" width="80" height="20" as="geometry"/></mxCell><mxCell id="17" value="/functx-1.0" style="text" vertex="1" parent="15"><mxGeometry x="35" y="70" width="80" height="20" as="geometry"/></mxCell><mxCell id="18" value="dependencies" style="text" vertex="1" parent="15"><mxGeometry x="35" y="100" width="80" height="20" as="geometry"/></mxCell><mxCell id="19" value="depx repository is contained&#xa;inside of a github repository" style="text" vertex="1" parent="1"><mxGeometry x="277" y="223" width="180" height="50" as="geometry"/></mxCell><mxCell id="20" value="get info on packages&#xa; on the website" style="text" vertex="1" parent="1"><mxGeometry x="450" y="72" width="80" height="20" as="geometry"/></mxCell><mxCell id="14" value="install/remove&#xa;packages&#xa;" style="edgeStyle=none;startArrow=classic" edge="1" parent="1" source="4" target="15"><mxGeometry x="62.10526315789474" y="115.7179842866637" width="100" height="100" as="geometry"><mxPoint x="189.14649718733824" y="149" as="sourcePoint"/><mxPoint x="110" y="243.97579662480587" as="targetPoint"/></mxGeometry></mxCell><mxCell id="21" value="depx architecture" style="text;fontSize=14;fontStyle=5" vertex="1" parent="1"><mxGeometry x="8" y="6" width="150" height="30" as="geometry"/></mxCell><mxCell id="22" value="" style="line;strokeWidth=1" vertex="1" parent="1"><mxGeometry x="9" y="27" width="145" height="8" as="geometry"/></mxCell></root></mxGraphModel>